nttblink/__init__.py
nttblink/nttblink.py
nttblink/setup.py
nttblink-0.1.4.dist-info/METADATA
nttblink-0.1.4.dist-info/WHEEL
nttblink-0.1.4.dist-info/top_level.txt
nttblink-0.1.4.dist-info/RECORD
