Metadata-Version: 2.1
Name: nttblink
Version: 0.1.4
Summary: A small nttblink connector package
Author-email: Austin Arlint <austin.arlint@global.ntt>
Project-URL: Homepage, https://github.com/NTT-AM-DDD/python-nttblink
Project-URL: Bug Tracker, https://github.com/NTT-AM-DDD/python-nttblink/issues
Classifier: Programming Language :: Python :: 3
Classifier: License :: OSI Approved :: MIT License
Classifier: Operating System :: OS Independent
Requires-Python: >=3.7
